evergate/__init__.py
evergate/_internal/__init__.py
evergate/_internal/caches.py
evergate/_internal/requesting.py
evergate/_internal/tokenstorage.py
evergate/datamodel/__init__.py
evergate/datamodel/agent.py
evergate/datamodel/alliance.py
evergate/datamodel/asset.py
evergate/datamodel/blueprint.py
evergate/datamodel/character.py
evergate/datamodel/contact.py
evergate/datamodel/notification.py
evergate/datamodel/skill.py
evergate/datamodel/vector.py
evergate/procedure/__init__.py
evergate/procedure/alliance.py
evergate/procedure/asset.py
evergate/procedure/authorization.py
evergate/procedure/character.py
evergate/procedure/contact.py
evergate/procedure/skill.py
evergate-0.1.0.dist-info/WHEEL
evergate-0.1.0.dist-info/METADATA
evergate-0.1.0.dist-info/RECORD
