Metadata-Version: 2.1
Name: evergate
Version: 0.1.0
Summary: An API wrapper for Eve Online Swagger Interface
License: MIT
Author: frodo821
Author-email: sakaic2003@gmail.com
Requires-Python: >=3.11,<3.12
Classifier: License :: OSI Approved :: MIT License
Classifier: Programming Language :: Python :: 3
Classifier: Programming Language :: Python :: 3.11
Requires-Dist: pydantic (>=1.10.2,<2.0.0)
Requires-Dist: requests (>=2.28.1,<3.0.0)
